{
	"recentTransactions": [
		{
			"transactionNumber": "185-8745415-4124-14",
			"transactionDate": "11/15/2016 19:45",
			"transactionType": "Bank Withdrawal",
			"amount": "-$15,000.00",
			"balance": 262511.87
		},
		{
			"transactionNumber": "185-8715647-5821-63",
			"transactionDate": "11/14/2016 18:30",
			"transactionType": "ATM Withdrawal",
			"amount": "-$2,500.00",
			"balance": 277511.87
		},
		{
			"transactionNumber": "175-8741947-5862-54",
			"transactionDate": "11/13/2016 17:45",
			"transactionType": "ATM Withdrawal",
			"amount": "-$2,500.00",
			"balance": 280011.87
		},
		{
			"transactionNumber": "164-8494947-0156-14",
			"transactionDate": "11/12/2016 18:18",
			"transactionType": "ATM Withdrawal",
			"amount": "-$2,500.00",
			"balance": 282511.87
		},
		{
			"transactionNumber": "157-4819871-4491-52",
			"transactionDate": "11/11/2016 21:56",
			"transactionType": "Bank Withdrawal",
			"amount": "-$8,000.00",
			"balance": 285011.87
		}
	]

}