{
	"accountInformation": {
		"accountNumber": "7348-6817-3828-1674",
		"accountType": "Savings",
		"dateOpened": "09/01/2014",
		"dateClosed": "--",
		"currentBalance": 36783.00,
		"accountLength": "2 years"
	},
	"branchInformation": {
		"address": "130 Fulton Street",
		"branchManager": "Dennis Mariner",
		"branchId": 4952732,
		"contactNo": "(688) 488-4544",
		"openCases": "11413 - Jack Reacher - In Progress",
		"caseHistory": [
			{
				"item": "478 - Scott Summers - Resolved"
			},
			{
				"item": "317 - Jean Logan - Resolved"
			}
		]
	},
	"currentHomeAddress": {
		"address": "229 Seventh Avenue",
		"city": "New York",
		"state": "NY",
		"zip": "10011",
		"phoneNumber": "(593) 380-3032",
		"cellPhoneNumber": "(814) 867-5653",
		"email": "dv2156@gmail.com"
	}
}